helloworld.py
helloworld_judy2k-0.0.1.dist-info/METADATA
helloworld_judy2k-0.0.1.dist-info/RECORD
helloworld_judy2k-0.0.1.dist-info/WHEEL
helloworld_judy2k-0.0.1.dist-info/top_level.txt
