Metadata-Version: 2.1
Name: helloworld-judy2k
Version: 0.0.1
Summary: Say hello!
Home-page: https://github.com/example/helloworld
Author: Mark Smith
Author-email: mark.smith@vonage.com
License: UNKNOWN
Platform: UNKNOWN
Classifier: Programming Language :: Python :: 3
Classifier: Programming Language :: Python :: 3.6
Classifier: Programming Language :: Python :: 3.7
Classifier: License :: OSI Approved :: GNU General Public License v2 or later (GPLv2+)
Classifier: Operating System :: OS Independent
